zope.traversing-5.0-py3.9-nspkg.pth
zope/traversing/__init__.py
zope/traversing/adapters.py
zope/traversing/api.py
zope/traversing/configure.zcml
zope/traversing/interfaces.py
zope/traversing/namespace.py
zope/traversing/publicationtraverse.py
zope/traversing/testing.py
zope/traversing/browser/__init__.py
zope/traversing/browser/absoluteurl.py
zope/traversing/browser/configure.zcml
zope/traversing/browser/interfaces.py
zope/traversing/browser/tests.py
zope/traversing/tests/__init__.py
zope/traversing/tests/ftesting.zcml
zope/traversing/tests/test_conveniencefunctions.py
zope/traversing/tests/test_dependencies.py
zope/traversing/tests/test_lang.py
zope/traversing/tests/test_namespacetrversal.py
zope/traversing/tests/test_presentation.py
zope/traversing/tests/test_publicationtraverse.py
zope/traversing/tests/test_skin.py
zope/traversing/tests/test_traverser.py
zope/traversing/tests/test_vh.py
zope/traversing/tests/test_vhosting.py
zope.traversing-5.0.dist-info/LICENSE.txt
zope.traversing-5.0.dist-info/METADATA
zope.traversing-5.0.dist-info/WHEEL
zope.traversing-5.0.dist-info/namespace_packages.txt
zope.traversing-5.0.dist-info/top_level.txt
zope.traversing-5.0.dist-info/RECORD
