Metadata-Version: 2.1
Name: zope.traversing
Version: 5.0
Summary: Resolving paths in the object hierarchy
Home-page: https://github.com/zopefoundation/zope.traversing
Author: Zope Foundation and Contributors
Author-email: zope-dev@zope.dev
License: ZPL 2.1
Keywords: zope traversal route URL view
Classifier: Development Status :: 5 - Production/Stable
Classifier: Intended Audience :: Developers
Classifier: License :: OSI Approved :: Zope Public License
Classifier: Programming Language :: Python
Classifier: Programming Language :: Python :: 3
Classifier: Programming Language :: Python :: 3.7
Classifier: Programming Language :: Python :: 3.8
Classifier: Programming Language :: Python :: 3.9
Classifier: Programming Language :: Python :: 3.10
Classifier: Programming Language :: Python :: 3.11
Classifier: Programming Language :: Python :: Implementation :: CPython
Classifier: Programming Language :: Python :: Implementation :: PyPy
Classifier: Natural Language :: English
Classifier: Operating System :: OS Independent
Classifier: Topic :: Internet :: WWW/HTTP
Classifier: Topic :: Software Development
Requires-Python: >=3.7
Provides-Extra: test
Provides-Extra: docs
License-File: LICENSE.txt
